COPYING
MANIFEST.in
README
health_socioeconomics_view.xml
setup.py
./__init__.py
./health_socioeconomics.py
./health_socioeconomics_view.xml
./tryton.cfg
./doc/index.rst
./locale/ar.po
./locale/de.po
./locale/el.po
./locale/es.po
./locale/fr.po
./locale/it_IT.po
./locale/ja_JP.po
./locale/lo.po
./locale/pt_BR.po
./locale/zh_CN.po
./security/access_rights.xml
./tests/__init__.py
./tests/test_health_socioeconomics.py
./view/gnuhealth_patient.xml
./view/gnuhealth_ses_assessment_form.xml
./view/gnuhealth_ses_assessment_tree.xml
./view/party_form.xml
locale/ar.po
locale/de.po
locale/el.po
locale/es.po
locale/fr.po
locale/it_IT.po
locale/ja_JP.po
locale/lo.po
locale/pt_BR.po
locale/zh_CN.po
security/access_rights.xml
trytond_health_socioeconomics.egg-info/PKG-INFO
trytond_health_socioeconomics.egg-info/SOURCES.txt
trytond_health_socioeconomics.egg-info/dependency_links.txt
trytond_health_socioeconomics.egg-info/entry_points.txt
trytond_health_socioeconomics.egg-info/not-zip-safe
trytond_health_socioeconomics.egg-info/requires.txt
trytond_health_socioeconomics.egg-info/top_level.txt
view/gnuhealth_patient.xml
view/gnuhealth_ses_assessment_form.xml
view/gnuhealth_ses_assessment_tree.xml
view/party_form.xml